sfaira/__init__.py
sfaira/_settings.py
sfaira/_version.py
sfaira/cli.py
sfaira/commands/__init__.py
sfaira/commands/annotate_dataloader.py
sfaira/commands/cache_control.py
sfaira/commands/consts.py
sfaira/commands/create_dataloader.py
sfaira/commands/export_h5ad.py
sfaira/commands/questionary.py
sfaira/commands/submit_pullrequest.py
sfaira/commands/test_dataloader.py
sfaira/commands/upgrade.py
sfaira/commands/utils.py
sfaira/commands/validate_dataloader.py
sfaira/commands/validate_h5ad.py
sfaira/commands/templates/multiple_datasets/cookiecutter.json
sfaira/commands/templates/multiple_datasets/hooks/__init__.py
sfaira/commands/templates/multiple_datasets/hooks/post_gen_project.py
sfaira/commands/templates/multiple_datasets/{{ cookiecutter.doi_sfaira_repr }}/__init__.py
sfaira/commands/templates/multiple_datasets/{{ cookiecutter.doi_sfaira_repr }}/extra_description.txt
sfaira/commands/templates/multiple_datasets/{{ cookiecutter.doi_sfaira_repr }}/{{ cookiecutter.id_without_doi }}.py
sfaira/commands/templates/multiple_datasets/{{ cookiecutter.doi_sfaira_repr }}/{{ cookiecutter.id_without_doi }}.yaml
sfaira/commands/templates/single_dataset/cookiecutter.json
sfaira/commands/templates/single_dataset/hooks/__init__.py
sfaira/commands/templates/single_dataset/hooks/post_gen_project.py
sfaira/commands/templates/single_dataset/{{ cookiecutter.doi_sfaira_repr }}/__init__.py
sfaira/commands/templates/single_dataset/{{ cookiecutter.doi_sfaira_repr }}/extra_description.txt
sfaira/commands/templates/single_dataset/{{ cookiecutter.doi_sfaira_repr }}/{{ cookiecutter.id_without_doi }}.py
sfaira/commands/templates/single_dataset/{{ cookiecutter.doi_sfaira_repr }}/{{ cookiecutter.id_without_doi }}.yaml
sfaira/consts/__init__.py
sfaira/consts/adata_fields.py
sfaira/consts/meta_data_files.py
sfaira/consts/ontologies.py
sfaira/consts/utils.py
sfaira/data/__init__.py
sfaira/data/utils.py
sfaira/data/dataloaders/__init__.py
sfaira/data/dataloaders/super_group.py
sfaira-0.3.12.dist-info/LICENSE
sfaira-0.3.12.dist-info/METADATA
sfaira-0.3.12.dist-info/WHEEL
sfaira-0.3.12.dist-info/entry_points.txt
sfaira-0.3.12.dist-info/top_level.txt
sfaira-0.3.12.dist-info/RECORD
