Metadata-Version: 2.1
Name: sfaira
Version: 0.3.12
Summary: sfaira is a model and a data repository for single-cell data in a single python package.
Home-page: UNKNOWN
Author: theislab
Author-email: david.fischer@helmholtz-muenchen.de
License: UNKNOWN
Platform: UNKNOWN
Classifier: Development Status :: 5 - Production/Stable
Classifier: Intended Audience :: Developers
Classifier: License :: OSI Approved :: BSD License
Classifier: Natural Language :: English
Classifier: Programming Language :: Python :: 3
Classifier: Programming Language :: Python :: 3.7
Classifier: Programming Language :: Python :: 3.8
License-File: LICENSE
Requires-Dist: anndata (>=0.7.6)
Requires-Dist: crossref-commons
Requires-Dist: dask
Requires-Dist: docutils
Requires-Dist: fuzzywuzzy
Requires-Dist: IPython
Requires-Dist: loompy
Requires-Dist: matplotlib
Requires-Dist: networkx
Requires-Dist: numba
Requires-Dist: numpy (>=1.16.4)
Requires-Dist: obonet
Requires-Dist: openpyxl
Requires-Dist: owlready2
Requires-Dist: pandas
Requires-Dist: pyarrow
Requires-Dist: pytest (>=6.2.2)
Requires-Dist: python-Levenshtein
Requires-Dist: PyYAML
Requires-Dist: scanpy (>=1.7.0)
Requires-Dist: scipy (>=1.2.1)
Requires-Dist: seaborn
Requires-Dist: sparse
Requires-Dist: tensorflow
Requires-Dist: torch
Requires-Dist: torchmetrics
Requires-Dist: tqdm
Requires-Dist: requests
Requires-Dist: versioneer
Requires-Dist: h5py
Requires-Dist: xlrd (==1.*)
Requires-Dist: zarr
Requires-Dist: rich (>=9.10.0)
Requires-Dist: click (>=7.1.2)
Requires-Dist: questionary (>=1.8.1)
Requires-Dist: packaging (>=20.8)
Requires-Dist: requests (>=2.25.1)
Requires-Dist: switchlang (>=0.1.0)
Requires-Dist: cookiecutter (>=1.7.2)
Requires-Dist: boltons
Requires-Dist: flatten-dict
Provides-Extra: extension
Requires-Dist: sfaira-extension ; extra == 'extension'
Provides-Extra: plotting_deps
Requires-Dist: seaborn ; extra == 'plotting_deps'
Requires-Dist: matplotlib ; extra == 'plotting_deps'
Requires-Dist: sklearn ; extra == 'plotting_deps'
Provides-Extra: tensorflow
